tempfolderpy/__init__.py
tempfolderpy/exceptions.py
tempy/__init__.py
tempy/exceptions.py
tempfolderpy-1.0.0.dist-info/METADATA
tempfolderpy-1.0.0.dist-info/WHEEL
tempfolderpy-1.0.0.dist-info/licence
tempfolderpy-1.0.0.dist-info/top_level.txt
tempfolderpy-1.0.0.dist-info/RECORD
